pyopn/__init__.py
pyopn/_version.py
pyopn/api.py
pyopn/base_namespace.py
pyopn/client.py
pyopn/constants.py
pyopn/exceptions.py
pyopn/core/dhcpv4.py
pyopn/core/dhcpv4_namespace.py
pyopn/core/kea.py
pyopn/core/kea_namespace.py
pyopn/tests/__init__.py
pyopn/tests/base.py
pyopn/tests/test_client.py
pyopn-0.2.0.dist-info/METADATA
pyopn-0.2.0.dist-info/WHEEL
pyopn-0.2.0.dist-info/licenses/LICENSE
pyopn-0.2.0.dist-info/RECORD
