Metadata-Version: 2.4
Name: pyopn
Version: 0.2.0
Summary:  A simple Python wrapper for the OPNsense REST API.
Project-URL: Homepage, https://github.com/alexchristy/PyOPN
Author-email: Alex Christy <a.christy@ufl.edu>
License:                     GNU GENERAL PUBLIC LICENSE
License-File: LICENSE
Classifier: Development Status :: 4 - Beta
Classifier: Intended Audience :: Developers
Classifier: Intended Audience :: System Administrators
Classifier: License :: OSI Approved :: GNU General Public License v3 (GPLv3)
Classifier: Operating System :: OS Independent
Classifier: Programming Language :: Python
Classifier: Programming Language :: Python :: 3
Classifier: Programming Language :: Python :: 3.10
Classifier: Topic :: Software Development :: Libraries
Classifier: Topic :: Software Development :: Libraries :: Python Modules
Classifier: Topic :: System :: Networking
Classifier: Topic :: System :: Systems Administration
Requires-Python: >=3.10
Requires-Dist: pbr>=1.6
Requires-Dist: requests>=2.14.2
Requires-Dist: validators>=0.34
